email_testview/__init__.py
email_testview/registry.py
email_testview/urls.py
email_testview/utils.py
email_testview/views.py
email_testview/templates/email_testview/emails_view.html
django_email_testview-0.1.2.dist-info/LICENSE
django_email_testview-0.1.2.dist-info/METADATA
django_email_testview-0.1.2.dist-info/WHEEL
django_email_testview-0.1.2.dist-info/top_level.txt
django_email_testview-0.1.2.dist-info/RECORD
