Metadata-Version: 2.1
Name: django-email-testview
Version: 0.1.2
Summary: Strongly opinionated way to handle emails with Django
Home-page: https://github.com/theartling/django-email-testview/
Author: Martin Brochhaus
Author-email: mbrochh@gmail.com
License: MIT License
Classifier: Environment :: Web Environment
Classifier: Framework :: Django
Classifier: Framework :: Django :: 2.2
Classifier: Intended Audience :: Developers
Classifier: License :: OSI Approved :: MIT License
Classifier: Operating System :: OS Independent
Classifier: Programming Language :: Python
Classifier: Programming Language :: Python :: 3.6
Classifier: Topic :: Internet :: WWW/HTTP
Classifier: Topic :: Internet :: WWW/HTTP :: Dynamic Content
License-File: LICENSE
Requires-Dist: Django (>=2)
Provides-Extra: dev
Requires-Dist: pytest ; extra == 'dev'
Requires-Dist: pytest-django ; extra == 'dev'
Requires-Dist: pytest-cov ; extra == 'dev'
Requires-Dist: fabric ; extra == 'dev'
Requires-Dist: mixer ; extra == 'dev'
